Workbook

Sheet Summary
B2: EU Data Analyst Job Market — Summary
B3: Adzuna postings, July 2026 snapshot
B5: Total Postings | C5: % with Salary Data | D5: Median Salary EUR (GB) | E5: Median Salary EUR (FR) | F5: Top Skill (by mentions)
B6: =COUNTA(RawJobs!$D$2:$D$3745) -> 3744 | C6: =COUNT(RawJobs!$G$2:$G$3745)/COUNTA(RawJobs!$D$2:$D$3745) -> 0.73424145 | D6: {=MEDIAN(IF(RawJobs!$D$2:$D$3745="gb",RawJobs!$G$2:$G$3745))} -> 57663.678 | E6: {=MEDIAN(IF(RawJobs!$D$2:$D$3745="fr",RawJobs!$G$2:$G$3745))} -> 43500 | F6: {=INDEX(RawSkills!$B$2:$B$521,MATCH(MAX(COUNTIF(RawSkills!$B$2:$B$521,RawSkills!$B$2:$B$521)),COUNTIF(RawSkills!$B$2:$B$521,RawSkills!$B$2:$B$521),0))} -> sql
B9: Postings by Country
B10: Country | C10: Postings
B11: DE | C11: =COUNTIF(RawJobs!$D$2:$D$3745,B11) -> 277
B12: ES | C12: =COUNTIF(RawJobs!$D$2:$D$3745,B12) -> 68
B13: FR | C13: =COUNTIF(RawJobs!$D$2:$D$3745,B13) -> 1212
B14: GB | C14: =COUNTIF(RawJobs!$D$2:$D$3745,B14) -> 1962
B15: IT | C15: =COUNTIF(RawJobs!$D$2:$D$3745,B15) -> 111
B16: NL | C16: =COUNTIF(RawJobs!$D$2:$D$3745,B16) -> 114

Sheet RawJobs
A1: id | B1: title | C1: company | D1: country | E1: city | F1: created | G1: salary_eur | H1: contract_time | I1: is_junior | J1: is_remote
A2: 5770828727 | B2: Senior IT Business Analyst (m/w/d) | C2: Trianel GmbH | D2: de | E2: Aachen | F2: 2026-06-20 | I2: f | J2: f
A3: 5762643172 | B3: Salesforce Technical Business Analyst (m/w/d) | C3: BELFOR Europe GmbH | D3: de | E3: Duisburg | F3: 2026-06-13 | I3: f | J3: f
A4: 5766906690 | B4: IT Business Analyst Production (m/w/d) | C4: Liebherr-Hydraulikbagger GmbH | D4: de | E4: Kirchdorf | F4: 2026-06-17 | I4: f | J4: f
A5: 5751502749 | B5: SAP Business Analyst SD/LE (m/w/d) | C5: Capri Sun GmbH | D5: de | E5: Deutschland | F5: 2026-06-04 | I5: f | J5: f
A6: 5773180876 | B6: Senior IT-Consultant / Business Analyst Versicherungen (all genders) | C6: adesso SE | D6: de | E6: Düsseldorf | F6: 2026-06-23 | I6: f | J6: f
A7: 5786428751 | B7: Duales Studium Wirtschaftsinformatik B.Sc. – IT-Business-Analyst | C7: Atruvia AG | D7: de | E7: Münster | F7: 2026-07-03 | I7: f | J7: f
A8: 5775008628 | B8: IT Business Analyst Payments (w/m/d) | C8: Aareal Bank AG | D8: de | E8: Wiesbaden | F8: 2026-06-24 | I8: f | J8: f
A9: 5775740862 | B9: IT Business Analyst (gn) - Production | C9: The Quality Group GmbH | D9: de | E9: Hamburg | F9: 2026-06-25 | I9: f | J9: t
A10: 5775009160 | B10: IT Business Analyst - Kontoführung Kernbanksystem (w/m/d) | C10: Aareal Bank AG | D10: de | E10: Wiesbaden | F10: 2026-06-24 | I10: f | J10: f
A11: 5777028058 | B11: Business Analyst | C11: Gattaca PBS | D11: de | E11: München | F11: 2026-06-26 | G11: 77500 | H11: full_time | I11: f | J11: f
A12: 5768047030 | B12: Senior Business Analyst - Trade Life Cycle Management - Commodity Markets (f/m/d) | C12: E.ON Energy Markets GmbH | D12: de | E12: Essen | F12: 2026-06-18 | H12: full_time | I12: f | J12: f
A13: 5785690789 | B13: IT Domain Architect im Bereich Governance Administration (m/w/d) | C13: Liebherr-Aerospace Lindenberg GmbH | D13: de | E13: Lindenberg | F13: 2026-07-02 | I13: f | J13: f
A14: 5768046989 | B14: Engineer as Senior Business Analyst - Coordinate Change Delivery - Risk Management (f/m/d) | C14: E.ON Energy Markets GmbH | D14: de | E14: Essen | F14: 2026-06-18 | H14: full_time | I14: f | J14: f
A15: 5783622139 | B15: IT Business Solution Analyst (m/w/d) | C15: Liebherr-Hausgeräte Ochsenhausen GmbH | D15: de | E15: Ochsenhausen | F15: 2026-07-01 | I15: f | J15: f
A16: 5766895115 | B16: Senior Business Implementation Analyst (f/m/d) | C16: E.ON Energy Markets GmbH | D16: de | E16: Essen | F16: 2026-06-17 | H16: full_time | I16: f | J16: f
A17: 5773180002 | B17: Consultant Digitalisierung - Kreditgeschäft / Wertpapiergeschäft / Projektmanagement (m/w/d) | C17: crossconsulting GmbH | D17: de | E17: Köln | F17: 2026-06-23 | I17: f | J17: f
A18: 5768046997 | B18: Economist as Senior Business Implementation Analyst - Organize Business Testing (f/m/d) | C18: E.ON Energy Markets GmbH | D18: de | E18: Essen | F18: 2026-06-18 | H18: full_time | I18: f | J18: f
A19: 5782063320 | B19: Solution Architect Application Management (m/w/d) | C19: TKMS GmbH | D19: de | E19: Hamburg | F19: 2026-06-30 | I19: f | J19: f
A20: 5772608881 | B20: Application Manager Zahlungsverkehr (m/w/d) | C20: Hanseatic Bank | D20: de | E20: Hamburg | F20: 2026-06-22 | I20: f | J20: f
A21: 5681676555 | B21: Data Analyst (m/w/d) | C21: Topmotive | D21: de | E21: Bargteheide | F21: 2026-03-28 | I21: f | J21: f
A22: 5764839537 | B22: Business Analyst (BillingPlatform) | C22: Darwin Recruitment | D22: de | E22: Berlin | F22: 2026-06-16 | H22: full_time | I22: f | J22: t
A23: 5692242739 | B23: Data Business Analyst | C23: Net2aspire | D23: de | E23: Deutschland | F23: 2026-04-07 | I23: f | J23: t
A24: 5760756783 | B24: Bilingual Business Analyst | C24: TechBiz Global GmbH | D24: de | E24: Deutschland | F24: 2026-06-12 | H24: full_time | I24: f | J24: t
A25: 5120304918 | B25: IT Business Analyst | C25: Micro IT Global | D25: de | E25: Deutschland | F25: 2025-03-31 | I25: f | J25: f
A26: 5773180453 | B26: IT-Systemadministrator - Netzwerk / Sicherheit / Azure (m/w/d) | C26: mbi GmbH | D26: de | E26: Wetzlar | F26: 2026-06-23 | I26: f | J26: f
A27: 5782346188 | B27: Business Analyst – Web Banking | C27: Avaloq | D27: de | E27: Berlin | F27: 2026-06-30 | I27: f | J27: f
A28: 5784961764 | B28: Senior Business Analyst:in im Consulting | C28: viadee Unternehmensberatung AG | D28: de | E28: Hainholz | F28: 2026-07-02 | G28: 72000 | H28: full_time | I28: f | J28: f
A29: 5784961630 | B29: Senior Business Analyst:in Reinsurance | C29: HDI Global | D29: de | E29: Bothfeld | F29: 2026-07-02 | G29: 71000 | H29: full_time | I29: f | J29: f
A30: 5785744507 | B30: Senior Business Analyst (all genders) | C30: SCAYLE | D30: de | E30: Deutschland | F30: 2026-07-02 | I30: f | J30: f
A31: 5785744484 | B31: Senior Business Analyst (all genders) | C31: SCAYLE | D31: de | E31: Deutschland | F31: 2026-07-02 | I31: f | J31: f
A32: 5763829165 | B32: IT Business Analyst (gn) - Production | C32: Bewerbung als IT Business Analyst | D32: de | E32: Hamburg | F32: 2026-06-14 | I32: f | J32: t
A33: 5757612654 | B33: Business Analyst:in (w/m/d) | C33: Ibykus | D33: de | E33: Daberstedt | F33: 2026-06-09 | H33: full_time | I33: f | J33: f
A34: 5752975938 | B34: Business Analyst (m/w/d) | C34: Finanz Informatik GmbH & Co. KG | D34: de | E34: Region Hannover (Kreis) | F34: 2026-06-05 | H34: full_time | I34: f | J34: f
A35: 5727111286 | B35: Business Analyst (m/w/d) | C35: blau direkt | D35: de | E35: Moisling | F35: 2026-05-12 | H35: full_time | I35: f | J35: f
A36: 5727349991 | B36: Business Analyst (m/w/d) | C36: blau direkt | D36: de | E36: Moisling | F36: 2026-05-12 | H36: full_time | I36: f | J36: f
A37: 5727129265 | B37: Business Analyst (m/w/d) | C37: Blueforte | D37: de | E37: Hamburg-Altstadt | F37: 2026-05-12 | H37: full_time | I37: f | J37: f
A38: 5645499831 | B38: Business Analyst (m/w/d) | C38: Striped Giraffe Innovation & Strategy GmbH | D38: de | E38: München | F38: 2026-02-25 | H38: full_time | I38: f | J38: f
A39: 5784960931 | B39: Business Analyst Zahlungsverkehr (all genders) | C39: adesso insurance solutions GmbH | D39: de | E39: Benninghofen | F39: 2026-07-02 | G39: 70000 | H39: full_time | I39: f | J39: f
A40: 5727299297 | B40: Senior Business Analyst (m/w/d) | C40: aixigo | D40: de | E40: Deutschland | F40: 2026-05-12 | H40: full_time | I40: f | J40: f
A41: 5784961034 | B41: Salesforce Business Analyst (m/w/d) | C41: BELFOR Europe GmbH | D41: de | E41: Großenbaum | F41: 2026-07-02 | G41: 51000 | H41: full_time | I41: f | J41: f
A42: 5770469478 | B42: Business Analyst Vertriebssteuerung (m/w/d) | C42: Finanz Informatik GmbH & Co. KG | D42: de | E42: Region Hannover (Kreis) | F42: 2026-06-20 | H42: full_time | I42: f | J42: f
A43: 5752975962 | B43: Business Analyst Adressenrisiko (m/w/d) | C43: Finanz Informatik GmbH & Co. KG | D43: de | E43: Region Hannover (Kreis) | F43: 2026-06-05 | H43: full_time | I43: f | J43: f
A44: 5752975843 | B44: Business Analyst Disposition (m/w/d) | C44: Finanz Informatik GmbH & Co. KG | D44: de | E44: Region Hannover (Kreis) | F44: 2026-06-05 | H44: full_time | I44: f | J44: f
A45: 5752975995 | B45: Business Analyst Firmenkunden (m/w/d) | C45: Finanz Informatik GmbH & Co. KG | D45: de | E45: Region Hannover (Kreis) | F45: 2026-06-05 | H45: full_time | I45: f | J45: f
A46: 5782125766 | B46: Business Analyst in der Softwareentwicklung (m/w/d) | C46: Workwise GmbH | D46: de | E46: Friedrichstadt | F46: 2026-06-30 | H46: full_time | I46: f | J46: f
A47: 5782126091 | B47: Business Analyst in der Softwareentwicklung (m/w/d) | C47: Workwise GmbH | D47: de | E47: Langen (Hessen) | F47: 2026-06-30 | H47: full_time | I47: f | J47: f
A48: 5727350500 | B48: Business Analyst/Berater (m/w/d) | C48: attempto & Co. KG | D48: de | E48: Deisenhofen | F48: 2026-05-12 | H48: full_time | I48: f | J48: f
A49: 5762010199 | B49: Senior IT Business Analyst/ Requirements Engineer* | C49: Accso – Accelerated Solutions GmbH | D49: de | E49: Altstadt-Nord | F49: 2026-06-13 | G49: 73500 | H49: full_time | I49: f | J49: f
A50: 5784960014 | B50: Business Analyst CRM (m/w/d) | C50: Markant Gruppe | D50: de | E50: Zunsweier | F50: 2026-07-02 | G50: 62500 | H50: full_time | I50: f | J50: f
A51: 5784960880 | B51: Business Analyst Gesetzliche Krankenversicherung (all genders) | C51: adesso SE | D51: de | E51: Derendorf | F51: 2026-07-02 | G51: 60000 | H51: full_time | I51: f | J51: f
A52: 5782346114 | B52: Senior Business Analyst* Input Management mit Fokus KI | C52: BarmeniaGothaer AG | D52: de | E52: Köln | F52: 2026-06-30 | I52: f | J52: f
A53: 5782346216 | B53: Business Analyst Incentive Management (m/w/d) | C53: Ströer Media Deutschland GmbH | D53: de | E53: Köln | F53: 2026-06-30 | I53: f | J53: f
A54: 5727313178 | B54: Senior Business Analyst (Extern) (m/w/d) | C54: aixigo | D54: de | E54: Deutschland | F54: 2026-05-12 | H54: full_time | I54: f | J54: f
A55: 5784960867 | B55: Senior IT-Consultant / Business Analyst (all genders) | C55: adesso SE | D55: de | E55: Derendorf | F55: 2026-07-02 | G55: 60000 | H55: full_time | I55: f | J55: f
A56: 5766268590 | B56: Business Analyst - Anforderungsmanagement (m/w/d) in Köln | C56: IBM Client Innovation Center Germany GmbH von bms | D56: de | E56: Köln | F56: 2026-06-17 | H56: full_time | I56: f | J56: f
A57: 5766268588 | B57: Business Analyst - Anforderungsmanagement (m/w/d) in München | C57: IBM Client Innovation Center Germany GmbH von bms | D57: de | E57: München | F57: 2026-06-17 | H57: full_time | I57: f | J57: f
A58: 5766268626 | B58: Business Analyst - Anforderungsmanagement (m/w/d) in Magdeburg | C58: IBM Client Innovation Center Germany GmbH von bms | D58: de | E58: Magdeburg | F58: 2026-06-17 | H58: full_time | I58: f | J58: f
A59: 5784961868 | B59: IT Business Analyst Production (m/w/d) | C59: Liebherr-Hydraulikbagger GmbH | D59: de | E59: Kellmünz an der Iller | F59: 2026-07-02 | G59: 70000 | H59: full_time | I59: f | J59: f
A60: 5759157852 | B60: Salesforce Technical Business Analyst (m/w/d) | C60: BELFOR Europe | D60: de | E60: Großenbaum | F60: 2026-06-11 | H60: full_time | I60: f | J60: f
A61: 5752975954 | B61: Business Analyst Girocard Autorisierung (m/w/d) | C61: Finanz Informatik GmbH & Co. KG | D61: de | E61: Region Hannover (Kreis) | F61: 2026-06-05 | H61: full_time | I61: f | J61: f
A62: 5752975936 | B62: Business Analyst OSPlus Versicherungsprozesse (m/w/d) | C62: Finanz Informatik GmbH & Co. KG | D62: de | E62: Münster | F62: 2026-06-05 | H62: full_time | I62: f | J62: f
A63: 5770469193 | B63: Business Analyst Payment / Zahlungsverkehr (m/w/d) | C63: Finanz Informatik GmbH & Co. KG | D63: de | E63: Frankfurt am Main | F63: 2026-06-20 | H63: full_time | I63: f | J63: f
A64: 5752975949 | B64: Business Analyst mit KI-Hintergrund (m/w/d) | C64: Finanz Informatik GmbH & Co. KG | D64: de | E64: Münster | F64: 2026-06-05 | H64: full_time | I64: f | J64: f
A65: 5770469577 | B65: Business Analyst Nachhaltigkeitsszenarien in der Banksteuerung (m/w/d) | C65: Finanz Informatik GmbH & Co. KG | D65: de | E65: Region Hannover (Kreis) | F65: 2026-06-20 | H65: full_time | I65: f | J65: f
A66: 5735809215 | B66: Business Analyst (m/w/d) Data / CRM | C66: Elis Deutschland | D66: de | E66: Bahrenfeld | F66: 2026-05-21 | G66: 55000 | H66: full_time | I66: f | J66: f
A67: 5696042278 | B67: (Senior) IT Business Analyst (m/w/d) | C67: Holman | D67: de | E67: Deutschland | F67: 2026-04-10 | H67: full_time | I67: f | J67: f
A68: 5770476319 | B68: Business Analyst Banking/IT (m/w/d) | C68: Finanz Informatik Solutions Plus GmbH | D68: de | E68: Fellbach | F68: 2026-06-20 | H68: full_time | I68: f | J68: f
A69: 5784961170 | B69: Senior Business Analyst (m/w/d) – Prozessautomatisierung | C69: DZ HYP | D69: de | E69: Geist | F69: 2026-07-02 | G69: 72500 | H69: full_time | I69: f | J69: f
A70: 5743627761 | B70: Werkstudent IT Business Analyst (m/w/d) | C70: REWE digital | D70: de | E70: Eil | F70: 2026-05-28 | I70: t | J70: f
A71: 5775014768 | B71: Senior Java Fullstack Developer:in | C71: HDI Global | D71: de | E71: Hannover | F71: 2026-06-24 | I71: f | J71: f
A72: 5758068957 | B72: IT-Business Analyst (w/m/d) ab sofort | C72: RADAS Jobbörse & Personalvermittlung GmbH | D72: de | E72: Sonnenberg | F72: 2026-06-10 | G72: 55200 | H72: full_time | I72: f | J72: f
A73: 5761006900 | B73: Business Analyst (BSA) – R2R Process (m/f/d) | C73: REPA Deutschland GmbH | D73: de | E73: Bergkirchen | F73: 2026-06-12 | I73: f | J73: f
A74: 5766268586 | B74: Business Analyst - Anforderungsmanagement (m/w/d) in Frankfurt am Main | C74: IBM Client Innovation Center Germany GmbH von bms | D74: de | E74: Frankfurt am Main | F74: 2026-06-17 | H74: full_time | I74: f | J74: f
A75: 5784960193 | B75: SAP Business Analyst SD/LE (m/w/d) | C75: Capri Sun GmbH | D75: de | E75: Eppelheim | F75: 2026-07-02 | G75: 70000 | H75: full_time | I75: f | J75: f
A76: 5784961479 | B76: Duales Studium Wirtschaftsinformatik B.Sc. – IT-Business-Analyst | C76: Atruvia AG | D76: de | E76: Stadt Ascheberg | F76: 2026-07-02 | G76: 32500 | I76: f | J76: f
A77: 5727293417 | B77: Business Analyst (m/w/d) – Agentisierung & AI Automation | C77: Omnora | D77: de | E77: Sachsenhausen | F77: 2026-05-12 | H77: full_time | I77: f | J77: f
A78: 5774592283 | B78: Business-Analyst für digitale Online-Services (m/w/d) | C78: Finanz Informatik GmbH & Co. KG | D78: de | E78: Münster | F78: 2026-06-24 | H78: full_time | I78: f | J78: f
A79: 5752976012 | B79: IT Business Analyst Document Services (m/w/d) | C79: Finanz Informatik GmbH & Co. KG | D79: de | E79: Region Hannover (Kreis) | F79: 2026-06-05 | H79: full_time | I79: f | J79: f
A80: 5708711380 | B80: IT Business Analyst Document Services (m/w/d) | C80: Finanz Informatik & Co. KG | D80: de | E80: Bockenheim | F80: 2026-04-23 | H80: full_time | I80: f | J80: f
A81: 5725371047 | B81: Senior IT Business Analyst (m/w/d) in der Finanzdienstleistungsberatung | C81: Bewerbung als Senior IT Business Analyst | D81: de | E81: Deutschland | F81: 2026-05-10 | I81: f | J81: f
A82: 5752975929 | B82: IT Business Analyst Archive Services (m/w/d) | C82: Finanz Informatik GmbH & Co. KG | D82: de | E82: Frankfurt am Main | F82: 2026-06-05 | H82: full_time | I82: f | J82: f
A83: 5708718741 | B83: IT Business Analyst Archive Services (m/w/d) | C83: Finanz Informatik & Co. KG | D83: de | E83: Centrum | F83: 2026-04-23 | H83: full_time | I83: f | J83: f
A84: 5752975750 | B84: Experte Business Analyst mit KI-Hintergrund (m/w/d) | C84: Finanz Informatik GmbH & Co. KG | D84: de | E84: Frankfurt am Main | F84: 2026-06-05 | H84: full_time | I84: f | J84: f
A85: 5682442334 | B85: Business Analyst Generative Artificial Intelligence (m/w/d) | C85: Finanz Informatik & Co. KG | D85: de | E85: Bemerode | F85: 2026-03-29 | H85: full_time | I85: f | J85: f
A86: 5784962040 | B86: Senior Business Analyst (m/w/d) Securities Services | C86: LBBW Landesbank Baden-Württemberg | D86: de | E86: Mitte | F86: 2026-07-02 | G86: 70000 | H86: full_time | I86: f | J86: f
A87: 5784960550 | B87: Business Analyst SAP CML & Banking (m/w/d) | C87: x1F GmbH | D87: de | E87: Mitte | F87: 2026-07-02 | G87: 84000 | H87: full_time | I87: f | J87: f
A88: 5784962336 | B88: Senior Business Analyst (m/w/d) digitale Transformationsprojekte | C88: SIGNAL IDUNA Gruppe | D88: de | E88: Neustadt | F88: 2026-07-02 | G88: 80000 | H88: full_time | I88: f | J88: f
A89: 5784960759 | B89: Senior IT Consultant / Business Analyst - Versicherungsmakler (all genders) | C89: adesso SE | D89: de | E89: Derendorf | F89: 2026-07-02 | G89: 60000 | H89: full_time | I89: f | J89: f
A90: 5736562190 | B90: IT Business Analyst - Quality Assurance (m/w/d) | C90: REWE digital | D90: de | E90: Eil | F90: 2026-05-21 | I90: f | J90: f
A91: 5575138081 | B91: Data Analyst Business Intelligence (w/m/d) | C91: KIND GmbH & Co. KG | D91: de | E91: Burgwedel | F91: 2026-01-09 | H91: full_time | I91: f | J91: f
A92: 5727130351 | B92: Product Owner / Business Analyst für die LORA Immobilienbewertungssoftware (m/w/d) | C92: on-geo | D92: de | E92: Andreasvorstadt | F92: 2026-05-12 | H92: full_time | I92: f | J92: f
A93: 5760102022 | B93: Digital Business Analyst - ERP for Service (d/f/m) | C93: Airbus Operations GmbH | D93: de | E93: Hamburg | F93: 2026-06-11 | I93: f | J93: f
A94: 5723931245 | B94: IT Business Analyst Warenwirtschaft im Stationary Retail (m/w/d) | C94: REWE digital | D94: de | E94: Eil | F94: 2026-05-09 | H94: full_time | I94: f | J94: f
A95: 5758056461 | B95: Werkstudent Business Analyst für Workflow-Automatisierungen / Digital Transformation (all genders) | D95: de | E95: Langenhagen | F95: 2026-06-10 | I95: t | J95: f
A96: 5723214534 | B96: Senior IT Business Analyst (m/w/d) in der Finanzdienstleistungsberatung - Capco | C96: Capco | D96: de | E96: Frankfurt am Main | F96: 2026-05-08 | I96: f | J96: f
A97: 5784960483 | B97: (Senior) Business Analyst OSPlus (m/w/d) Core Banking | C97: x1F GmbH | D97: de | E97: Deutschland | F97: 2026-07-02 | G97: 84000 | H97: full_time | I97: f | J97: f
A98: 5785682846 | B98: SAP S/4HANA Application Owner (m/f/d) | C98: CHG-MERIDIAN | D98: de | E98: Deutschland | F98: 2026-07-02 | I98: f | J98: f
A99: 5696055633 | B99: (Junior) IT Business Analyst / Requirements Engineer (w/m/d) - Standort Ulm | C99: Axians Infoma | D99: de | E99: Ermingen | F99: 2026-04-10 | H99: full_time | I99: t | J99: f
A100: 5775013733 | B100: Senior Java Developer:in | C100: HDI Global | D100: de | E100: Hannover | F100: 2026-06-24 | I100: f | J100: f
...

Sheet RawSkills
A1: job_id | B1: skill | C1: country
A2: 5760756783 | B2: english | C2: de
A3: 5773180453 | B3: azure | C3: de
A4: 5784962080 | B4: sql | C4: de
A5: 5779504932 | B5: azure | C5: de
A6: 5768350720 | B6: r | C6: de
A7: 5768350720 | B7: power bi | C7: de
A8: 5768350720 | B8: python | C8: de
A9: 5768350720 | B9: sql | C9: de
A10: 5727331636 | B10: tableau | C10: de
A11: 5727331636 | B11: power bi | C11: de
A12: 5781277991 | B12: power bi | C12: de
A13: 5784961742 | B13: azure | C13: de
... A521: 5777174690 | B521: python | C521: nl

Sheet Pivot_Country
A1: Country | B1: Postings | C1: Median Salary EUR
A2: DE | B2: =COUNTIF(RawJobs!$D$2:$D$3745,A2) -> 277 | C2: {=IFERROR(MEDIAN(IF(RawJobs!$D$2:$D$3745=A2,RawJobs!$G$2:$G$3745)),"n/a")} -> 68000
A3: ES | B3: =COUNTIF(RawJobs!$D$2:$D$3745,A3) -> 68 | C3: {=IFERROR(MEDIAN(IF(RawJobs!$D$2:$D$3745=A3,RawJobs!$G$2:$G$3745)),"n/a")} -> 42500
A4: FR | B4: =COUNTIF(RawJobs!$D$2:$D$3745,A4) -> 1212 | C4: {=IFERROR(MEDIAN(IF(RawJobs!$D$2:$D$3745=A4,RawJobs!$G$2:$G$3745)),"n/a")} -> 43500
A5: GB | B5: =COUNTIF(RawJobs!$D$2:$D$3745,A5) -> 1962 | C5: {=IFERROR(MEDIAN(IF(RawJobs!$D$2:$D$3745=A5,RawJobs!$G$2:$G$3745)),"n/a")} -> 57663.678
A6: IT | B6: =COUNTIF(RawJobs!$D$2:$D$3745,A6) -> 111 | C6: {=IFERROR(MEDIAN(IF(RawJobs!$D$2:$D$3745=A6,RawJobs!$G$2:$G$3745)),"n/a")} -> 32750
A7: NL | B7: =COUNTIF(RawJobs!$D$2:$D$3745,A7) -> 114 | C7: {=IFERROR(MEDIAN(IF(RawJobs!$D$2:$D$3745=A7,RawJobs!$G$2:$G$3745)),"n/a")} -> 52359

Sheet Pivot_Skills
A1: Skill | B1: Mentions
A2: sql | B2: =COUNTIF(RawSkills!$B$2:$B$521,A2) -> 116
A3: power bi | B3: =COUNTIF(RawSkills!$B$2:$B$521,A3) -> 100
A4: python | B4: =COUNTIF(RawSkills!$B$2:$B$521,A4) -> 58
A5: azure | B5: =COUNTIF(RawSkills!$B$2:$B$521,A5) -> 57
A6: excel | B6: =COUNTIF(RawSkills!$B$2:$B$521,A6) -> 41
A7: gcp | B7: =COUNTIF(RawSkills!$B$2:$B$521,A7) -> 26
A8: snowflake | B8: =COUNTIF(RawSkills!$B$2:$B$521,A8) -> 24
A9: tableau | B9: =COUNTIF(RawSkills!$B$2:$B$521,A9) -> 21
A10: aws | B10: =COUNTIF(RawSkills!$B$2:$B$521,A10) -> 12
A11: english | B11: =COUNTIF(RawSkills!$B$2:$B$521,A11) -> 10
A12: sas | B12: =COUNTIF(RawSkills!$B$2:$B$521,A12) -> 10
A13: r | B13: =COUNTIF(RawSkills!$B$2:$B$521,A13) -> 9
... A16: dax | B16: =COUNTIF(RawSkills!$B$2:$B$521,A16) -> 6
